django_xhtml2pdf/__init__.py
django_xhtml2pdf/models.py
django_xhtml2pdf/utils.py
django_xhtml2pdf/views.py
lanshark_django_xhtml2pdf-0.0.7.dist-info/LICENSE
lanshark_django_xhtml2pdf-0.0.7.dist-info/METADATA
lanshark_django_xhtml2pdf-0.0.7.dist-info/WHEEL
lanshark_django_xhtml2pdf-0.0.7.dist-info/top_level.txt
lanshark_django_xhtml2pdf-0.0.7.dist-info/RECORD
