Metadata-Version: 2.1
Name: lanshark-django-xhtml2pdf
Version: 0.0.7
Summary: A Django app to generate pdfs from templates
Home-page: https://gitlab.com/lansharkconsulting/django/lanshark-django-xhtml2pdf/
Author: Scott Sharkey
Author-email: ssharkey@lanshark.com
License: BSD License
Platform: OS Independent
Classifier: Environment :: Web Environment
Classifier: Framework :: Django
Classifier: Framework :: Django :: 1.11
Classifier: Framework :: Django :: 2.0
Classifier: Intended Audience :: Developers
Classifier: License :: OSI Approved :: BSD License
Classifier: Operating System :: OS Independent
Classifier: Programming Language :: Python
Classifier: Programming Language :: Python :: 2
Classifier: Programming Language :: Python :: 2.7
Classifier: Programming Language :: Python :: 3
Classifier: Programming Language :: Python :: 3.6
Classifier: Programming Language :: Python :: 3.8
Classifier: Topic :: Software Development :: Libraries :: Application Frameworks
Classifier: Topic :: Internet :: WWW/HTTP :: Dynamic Content
Requires-Dist: Django
Requires-Dist: xhtml2pdf
